{"analysisResults":[[{"matchingRatio":0.9895663791232638,"averageDistanceRatio":0.000002187252895527091,"mismatchingAverageDistanceRatio":0.00020963507504897155},{"matchingRatio":0.9990573459201388,"averageDistanceRatio":0.000002033261608316147,"mismatchingAverageDistanceRatio":0.00218535111737134},{"matchingRatio":0.9997982449001737,"averageDistanceRatio":7.862467739020758e-7,"mismatchingAverageDistanceRatio":0.006736734430310372}],[{"matchingRatio":0.05192226833767361,"averageDistanceRatio":0.00022877888875611553,"mismatchingAverageDistanceRatio":0.00024130815556123504},{"matchingRatio":0.1294894748263889,"averageDistanceRatio":0.00020294897196787912,"mismatchingAverageDistanceRatio":0.0002615348625799152},{"matchingRatio":0.9989793565538194,"averageDistanceRatio":0.0000035540364271242024,"mismatchingAverageDistanceRatio":0.006321851785249223}]],"lighting":"../../../shared-assets/environments/lightroom_14b.hdr","dimensions":{"width":768,"height":768},"target":{"x":0,"y":0.9,"z":0},"orbit":{"theta":0,"phi":90,"radius":3.6},"verticalFoV":45,"name":"khronos-BrainStem","model":"../../../shared-assets/models/glTF-Sample-Models/2.0/BrainStem/glTF-Binary/BrainStem.glb"}