{"analysisResults":[[{"matchingRatio":0.9592420789930556,"averageDistanceRatio":0.000009334290357246146,"mismatchingAverageDistanceRatio":0.0002290178234472692},{"matchingRatio":0.9979231092664931,"averageDistanceRatio":0.000008978357192711858,"mismatchingAverageDistanceRatio":0.004351377033048929},{"matchingRatio":0.9996219211154513,"averageDistanceRatio":0.00000693121350003548,"mismatchingAverageDistanceRatio":0.021172416801076926}],[{"matchingRatio":0.05250718858506945,"averageDistanceRatio":0.0021062152997898416,"mismatchingAverageDistanceRatio":0.00222293538738784},{"matchingRatio":0.13660176595052084,"averageDistanceRatio":0.0020805075709696636,"mismatchingAverageDistanceRatio":0.0024380701730708303},{"matchingRatio":0.8837348090277778,"averageDistanceRatio":0.001504904851297732,"mismatchingAverageDistanceRatio":0.015783425645718253}]],"lighting":"../../../shared-assets/environments/lightroom_14b.hdr","dimensions":{"width":768,"height":768},"target":{"x":0,"y":0,"z":0},"orbit":{"theta":0,"phi":90,"radius":3},"verticalFoV":45,"name":"khronos-Suzanne","model":"../../../shared-assets/models/glTF-Sample-Models/2.0/Suzanne/glTF/Suzanne.gltf"}